pyvat/__init__.py
pyvat/countries.py
pyvat/exceptions.py
pyvat/item_type.py
pyvat/party.py
pyvat/registries.py
pyvat/result.py
pyvat/utils.py
pyvat/vat_charge.py
pyvat/vat_rules.py
pyvat/xml_utils.py
pyvat-1.3.17.dist-info/AUTHORS
pyvat-1.3.17.dist-info/LICENSE
pyvat-1.3.17.dist-info/METADATA
pyvat-1.3.17.dist-info/WHEEL
pyvat-1.3.17.dist-info/top_level.txt
pyvat-1.3.17.dist-info/RECORD
