Metadata-Version: 2.1
Name: pyvat
Version: 1.3.17
Summary: VAT validation for Python
Home-page: https://www.iconfinder.com
Author: Iconfinder
Author-email: support@iconfinder.com
Project-URL: Issue Tracker, https://github.com/iconfinder/pyvat/issues
Classifier: Development Status :: 5 - Production/Stable
Classifier: Intended Audience :: Developers
Classifier: Natural Language :: English
Classifier: License :: OSI Approved :: Apache Software License
Classifier: Programming Language :: Python
Classifier: Programming Language :: Python :: 2.7
Classifier: Programming Language :: Python :: 3.3
Classifier: Programming Language :: Python :: 3.4
Classifier: Programming Language :: Python :: 3.5
Classifier: Programming Language :: Python :: 3.7
License-File: LICENSE
License-File: AUTHORS
Requires-Dist: requests (<3.0,>=1.0.0)
Requires-Dist: pycountry
Requires-Dist: enum34 ; python_version < "3.4"
